{
  "game": {
    "id": "pd0n7o21",
    "name": "Harry Potter and the Chamber of Secrets (PS2)",
    "slug": "hp2ps2"
  },
  "category": {
    "id": "rklo0owk",
    "name": "Any%"
  },
  "runCount": 26,
  "runs": [
    {
      "place": 1,
      "run": {
        "id": "y6vp15jm",
        "weblink": "http://www.speedrun.com/hp2ps2/run/y6vp15jm",
        "game": "pd0n7o21",
        "level": null,
        "category": "rklo0owk",
        "videos": {
          "links": [
            {
              "uri": "https://youtu.be/CV1gZKX0uf0"
            }
          ]
        },
        "comment": "![](/static/blob/xz0gwmel.png)",
        "status": {
          "status": "verified",
          "examiner": "48gl4k2x",
          "verify-date": "2024-02-29T13:38:42Z"
        },
        "players": [
          {
            "rel": "user",
            "id": "8l049d48",
            "uri": "http://www.speedrun.com/api/v1/users/8l049d48"
          }
        ],
        "date": "2024-02-29",
        "submitted": "2024-02-29T06:14:34Z",
        "times": {
          "primary": "PT39M43S",
          "primary_t": 2383,
          "realtime": "PT56M58S",
          "realtime_t": 3418,
          "realtime_noloads": "PT39M43S",
          "realtime_noloads_t": 2383,
          "ingame": null,
          "ingame_t": 0
        },
        "system": {
          "platform": "n5e17e27",
          "emulated": true,
          "region": "pr184lqn"
        },
        "splits": null,
        "values": {
          "yn20gk2l": "qvv4y7rq"
        }
      }
    },
    {
      "place": 2,
      "run": {
        "id": "zp5xkrvy",
        "weblink": "http://www.speedrun.com/hp2ps2/run/zp5xkrvy",
        "game": "pd0n7o21",
        "level": null,
        "category": "rklo0owk",
        "videos": {
          "links": [
            {
              "uri": "https://www.youtube.com/watch?v=eXl-KrPsvxQ"
            }
          ]
        },
        "comment": "Had to mute the vod for 1min10 at 23:07, accidentally put some copyrighted song and only realized a bit after lol\n\nNothing special about this, had to reload my save after early sickle and no leaky cauldron lagjump so there's like 40ish to save there, I did go for the new flipendo switch strat in borgin and burkes but didn't really save any time with it lol\n\nWithout willow fight skip this can probably go to at least a 38 but hey, first sub 40 :D",
        "status": {
          "status": "verified",
          "examiner": "48gl4k2x",
          "verify-date": "2026-01-08T15:47:28Z"
        },
        "players": [
          {
            "rel": "user",
            "id": "48gl4k2x",
            "uri": "http://www.speedrun.com/api/v1/users/48gl4k2x"
          }
        ],
        "date": "2026-01-08",
        "submitted": "2026-01-08T15:47:28Z",
        "times": {
          "primary": "PT39M57S",
          "primary_t": 2397,
          "realtime": "PT1H6M30S",
          "realtime_t": 3990,
          "realtime_noloads": "PT39M57S",
          "realtime_noloads_t": 2397,
          "ingame": null,
          "ingame_t": 0
        },
        "system": {
          "platform": "n5e17e27",
          "emulated": false,
          "region": "pr184lqn"
        },
        "splits": null,
        "values": {
          "yn20gk2l": "139v60r1"
        }
      }
    },
    {
      "place": 3,
      "run": {
        "id": "m30o3e4m",
        "weblink": "http://www.speedrun.com/hp2ps2/run/m30o3e4m",
        "game": "pd0n7o21",
        "level": null,
        "category": "rklo0owk",
        "videos": {
          "links": [
            {
              "uri": "https://youtu.be/mi2kJ1sVcjU"
            }
          ]
        },
        "comment": null,
        "status": {
          "status": "verified",
          "examiner": "8l049d48",
          "verify-date": "2024-02-26T03:44:15Z"
        },
        "players": [
          {
            "rel": "user",
            "id": "98r46qj1",
            "uri": "http://www.speedrun.com/api/v1/users/98r46qj1"
          }
        ],
        "date": "2024-02-25",
        "submitted": "2024-02-26T03:29:57Z",
        "times": {
          "primary": "PT40M51S",
          "primary_t": 2451,
          "realtime": "PT1H7M21S",
          "realtime_t": 4041,
          "realtime_noloads": "PT40M51S",
          "realtime_noloads_t": 2451,
          "ingame": null,
          "ingame_t": 0
        },
        "system": {
          "platform": "n5e17e27",
          "emulated": false,
          "region": "pr184lqn"
        },
        "splits": {
          "rel": "splits.io",
          "uri": "https://splits.io/api/v3/runs/bruf"
        },
        "values": {
          "yn20gk2l": "139v60r1"
        }
      }
    },
    {
      "place": 4,
      "run": {
        "id": "z5815egz",
        "weblink": "http://www.speedrun.com/hp2ps2/run/z5815egz",
        "game": "pd0n7o21",
        "level": null,
        "category": "rklo0owk",
        "videos": {
          "links": [
            {
              "uri": "https://youtu.be/RA3pnphuF9Y"
            }
          ]
        },
        "comment": "lot of room in there",
        "status": {
          "status": "verified",
          "examiner": "j5v9dw68",
          "verify-date": "2024-02-23T22:48:05Z"
        },
        "players": [
          {
            "rel": "user",
            "id": "jop16m7x",
            "uri": "http://www.speedrun.com/api/v1/users/jop16m7x"
          }
        ],
        "date": "2021-02-14",
        "submitted": "2024-02-23T22:48:05Z",
        "times": {
          "primary": "PT43M38S",
          "primary_t": 2618,
          "realtime": "PT1H24S",
          "realtime_t": 3624,
          "realtime_noloads": "PT43M38S",
          "realtime_noloads_t": 2618,
          "ingame": null,
          "ingame_t": 0
        },
        "system": {
          "platform": "n5e17e27",
          "emulated": true,
          "region": "pr184lqn"
        },
        "splits": null,
        "values": {
          "yn20gk2l": "qvv4y7rq"
        }
      }
    },
    {
      "place": 5,
      "run": {
        "id": "y6vp3o1m",
        "weblink": "http://www.speedrun.com/hp2ps2/run/y6vp3o1m",
        "game": "pd0n7o21",
        "level": null,
        "category": "rklo0owk",
        "videos": {
          "links": [
            {
              "uri": "https://www.twitch.tv/videos/909251074"
            }
          ]
        },
        "comment": "Another WR improvement, this time utilising the all new WillowSkip (thanks to MikeKatz and SLS for helping to discover it), and SLS's Final Cutscene Skip.\n\nEarly game wasn't so great, but the 50s timesave makes up for it.",
        "status": {
          "status": "verified",
          "examiner": "j5v9dw68",
          "verify-date": "2024-02-23T22:49:24Z"
        },
        "players": [
          {
            "rel": "user",
            "id": "8rp55owj",
            "uri": "http://www.speedrun.com/api/v1/users/8rp55owj"
          }
        ],
        "date": "2021-02-11",
        "submitted": "2024-02-23T22:49:24Z",
        "times": {
          "primary": "PT44M",
          "primary_t": 2640,
          "realtime": "PT1H44S",
          "realtime_t": 3644,
          "realtime_noloads": "PT44M",
          "realtime_noloads_t": 2640,
          "ingame": null,
          "ingame_t": 0
        },
        "system": {
          "platform": "n5e17e27",
          "emulated": true,
          "region": "pr184lqn"
        },
        "splits": {
          "rel": "splits.io",
          "uri": "https://splits.io/api/v3/runs/75jp"
        },
        "values": {
          "yn20gk2l": "qvv4y7rq"
        }
      }
    },
    {
      "place": 6,
      "run": {
        "id": "y6vp39jm",
        "weblink": "http://www.speedrun.com/hp2ps2/run/y6vp39jm",
        "game": "pd0n7o21",
        "level": null,
        "category": "rklo0owk",
        "videos": {
          "links": [
            {
              "uri": "https://youtu.be/4GRhVgusjIQ"
            }
          ]
        },
        "comment": "bad imps and gytrashes",
        "status": {
          "status": "verified",
          "examiner": "j5v9dw68",
          "verify-date": "2024-02-23T22:12:15Z"
        },
        "players": [
          {
            "rel": "user",
            "id": "o8663w8z",
            "uri": "http://www.speedrun.com/api/v1/users/o8663w8z"
          }
        ],
        "date": "2021-02-13",
        "submitted": "2024-02-23T22:12:15Z",
        "times": {
          "primary": "PT44M36S",
          "primary_t": 2676,
          "realtime": "PT1H10M50S",
          "realtime_t": 4250,
          "realtime_noloads": "PT44M36S",
          "realtime_noloads_t": 2676,
          "ingame": null,
          "ingame_t": 0
        },
        "system": {
          "platform": "n5e17e27",
          "emulated": false,
          "region": "pr184lqn"
        },
        "splits": null,
        "values": {
          "yn20gk2l": "139v60r1"
        }
      }
    },
    {
      "place": 7,
      "run": {
        "id": "mepgpv3y",
        "weblink": "http://www.speedrun.com/hp2ps2/run/mepgpv3y",
        "game": "pd0n7o21",
        "level": null,
        "category": "rklo0owk",
        "videos": {
          "links": [
            {
              "uri": "https://www.youtube.com/watch?v=IRUVl72dQyk"
            }
          ]
        },
        "comment": null,
        "status": {
          "status": "verified",
          "examiner": "8l049d48",
          "verify-date": "2026-01-09T05:10:57Z"
        },
        "players": [
          {
            "rel": "user",
            "id": "j0nlz338",
            "uri": "http://www.speedrun.com/api/v1/users/j0nlz338"
          }
        ],
        "date": "2026-01-07",
        "submitted": "2026-01-09T01:00:57Z",
        "times": {
          "primary": "PT44M54S",
          "primary_t": 2694,
          "realtime": "PT1H4M1S",
          "realtime_t": 3841,
          "realtime_noloads": "PT44M54S",
          "realtime_noloads_t": 2694,
          "ingame": null,
          "ingame_t": 0
        },
        "system": {
          "platform": "n5e17e27",
          "emulated": true,
          "region": null
        },
        "splits": null,
        "values": {
          "yn20gk2l": "qvv4y7rq"
        }
      }
    },
    {
      "place": 8,
      "run": {
        "id": "y2ndgkjy",
        "weblink": "http://www.speedrun.com/hp2ps2/run/y2ndgkjy",
        "game": "pd0n7o21",
        "level": null,
        "category": "rklo0owk",
        "videos": {
          "links": [
            {
              "uri": "https://youtu.be/6XEFaVU6qRw?si=7wfBGiD5savZR5B3"
            }
          ]
        },
        "comment": "how exciting",
        "status": {
          "status": "verified",
          "examiner": "j5v9dw68",
          "verify-date": "2025-01-02T19:39:37Z"
        },
        "players": [
          {
            "rel": "user",
            "id": "xz04yre8",
            "uri": "http://www.speedrun.com/api/v1/users/xz04yre8"
          }
        ],
        "date": "2025-01-02",
        "submitted": "2025-01-02T12:10:57Z",
        "times": {
          "primary": "PT45M4S",
          "primary_t": 2704,
          "realtime": "PT1H4M17S",
          "realtime_t": 3857,
          "realtime_noloads": "PT45M4S",
          "realtime_noloads_t": 2704,
          "ingame": null,
          "ingame_t": 0
        },
        "system": {
          "platform": "n5e17e27",
          "emulated": true,
          "region": "pr184lqn"
        },
        "splits": null,
        "values": {
          "yn20gk2l": "qvv4y7rq"
        }
      }
    },
    {
      "place": 9,
      "run": {
        "id": "zn24wv3z",
        "weblink": "http://www.speedrun.com/hp2ps2/run/zn24wv3z",
        "game": "pd0n7o21",
        "level": null,
        "category": "rklo0owk",
        "videos": {
          "links": [
            {
              "uri": "https://youtu.be/Qrofh42WrM4"
            }
          ]
        },
        "comment": null,
        "status": {
          "status": "verified",
          "examiner": "j5v9dw68",
          "verify-date": "2024-02-23T22:51:48Z"
        },
        "players": [
          {
            "rel": "user",
            "id": "xkov3pk8",
            "uri": "http://www.speedrun.com/api/v1/users/xkov3pk8"
          }
        ],
        "date": "2021-11-05",
        "submitted": "2024-02-23T22:51:48Z",
        "times": {
          "primary": "PT45M17S",
          "primary_t": 2717,
          "realtime": "PT1H2M26S",
          "realtime_t": 3746,
          "realtime_noloads": "PT45M17S",
          "realtime_noloads_t": 2717,
          "ingame": null,
          "ingame_t": 0
        },
        "system": {
          "platform": "n5e17e27",
          "emulated": true,
          "region": "e6lxy1dz"
        },
        "splits": null,
        "values": {
          "yn20gk2l": "qvv4y7rq"
        }
      }
    },
    {
      "place": 10,
      "run": {
        "id": "zg9q4rdm",
        "weblink": "http://www.speedrun.com/hp2ps2/run/zg9q4rdm",
        "game": "pd0n7o21",
        "level": null,
        "category": "rklo0owk",
        "videos": {
          "links": [
            {
              "uri": "https://youtu.be/DcGWx2n9H0U"
            }
          ]
        },
        "comment": "First run of the Full Series Prep for next year. Wanted 1 run with the imp skip but could push this down further by adding the Diagon Alley strats",
        "status": {
          "status": "verified",
          "examiner": "8l049d48",
          "verify-date": "2025-12-10T19:39:11Z"
        },
        "players": [
          {
            "rel": "user",
            "id": "j2yzy968",
            "uri": "http://www.speedrun.com/api/v1/users/j2yzy968"
          }
        ],
        "date": "2025-12-10",
        "submitted": "2025-12-10T15:24:46Z",
        "times": {
          "primary": "PT45M29S",
          "primary_t": 2729,
          "realtime": "PT1H12M6S",
          "realtime_t": 4326,
          "realtime_noloads": "PT45M29S",
          "realtime_noloads_t": 2729,
          "ingame": null,
          "ingame_t": 0
        },
        "system": {
          "platform": "n5e17e27",
          "emulated": false,
          "region": "pr184lqn"
        },
        "splits": null,
        "values": {
          "yn20gk2l": "139v60r1"
        }
      }
    },
    {
      "place": 11,
      "run": {
        "id": "zgl73edm",
        "weblink": "http://www.speedrun.com/hp2ps2/run/zgl73edm",
        "game": "pd0n7o21",
        "level": null,
        "category": "rklo0owk",
        "videos": {
          "links": [
            {
              "uri": "https://www.youtube.com/watch?v=-Ltt5KF0s5g"
            }
          ]
        },
        "comment": "Finally a decent run.",
        "status": {
          "status": "verified",
          "examiner": "j5v9dw68",
          "verify-date": "2024-02-23T22:53:02Z"
        },
        "players": [
          {
            "rel": "user",
            "id": "zxz7o9jq",
            "uri": "http://www.speedrun.com/api/v1/users/zxz7o9jq"
          }
        ],
        "date": "2021-03-22",
        "submitted": "2024-02-23T22:53:02Z",
        "times": {
          "primary": "PT45M39S",
          "primary_t": 2739,
          "realtime": "PT1H2M28S",
          "realtime_t": 3748,
          "realtime_noloads": "PT45M39S",
          "realtime_noloads_t": 2739,
          "ingame": null,
          "ingame_t": 0
        },
        "system": {
          "platform": "n5e17e27",
          "emulated": true,
          "region": "pr184lqn"
        },
        "splits": null,
        "values": {
          "yn20gk2l": "qvv4y7rq"
        }
      }
    },
    {
      "place": 12,
      "run": {
        "id": "zp60nwgm",
        "weblink": "http://www.speedrun.com/hp2ps2/run/zp60nwgm",
        "game": "pd0n7o21",
        "level": null,
        "category": "rklo0owk",
        "videos": {
          "links": [
            {
              "uri": "https://www.twitch.tv/videos/909385145"
            }
          ]
        },
        "comment": "This is starting to get REALLY tight, loadless using Cyna's timer as well",
        "status": {
          "status": "verified",
          "examiner": "j5v9dw68",
          "verify-date": "2024-02-23T22:54:49Z"
        },
        "players": [
          {
            "rel": "user",
            "id": "81459vl8",
            "uri": "http://www.speedrun.com/api/v1/users/81459vl8"
          }
        ],
        "date": "2021-02-10",
        "submitted": "2024-02-23T22:54:49Z",
        "times": {
          "primary": "PT45M50S",
          "primary_t": 2750,
          "realtime": "PT1H2M58S",
          "realtime_t": 3778,
          "realtime_noloads": "PT45M50S",
          "realtime_noloads_t": 2750,
          "ingame": null,
          "ingame_t": 0
        },
        "system": {
          "platform": "n5e17e27",
          "emulated": true,
          "region": "pr184lqn"
        },
        "splits": {
          "rel": "splits.io",
          "uri": "https://splits.io/api/v3/runs/75ka"
        },
        "values": {
          "yn20gk2l": "qvv4y7rq"
        }
      }
    },
    {
      "place": 13,
      "run": {
        "id": "zpo80vvm",
        "weblink": "http://www.speedrun.com/hp2ps2/run/zpo80vvm",
        "game": "pd0n7o21",
        "level": null,
        "category": "rklo0owk",
        "videos": {
          "links": [
            {
              "uri": "https://youtu.be/D-ipd4hwcL4?t=17247"
            }
          ]
        },
        "comment": "Definitely the smoothest Any% run I have ever done of this game so I am quite happy with it! Didn't load the wrong save for once or other dumb mistakes like that and the gameplay was pretty solid overall, nice PB!\n\nSorry that this has to be retimed loadless but the tool does not support the finish dub 😅",
        "status": {
          "status": "verified",
          "examiner": "8l049d48",
          "verify-date": "2025-07-12T17:18:09Z"
        },
        "players": [
          {
            "rel": "user",
            "id": "7j4ozn58",
            "uri": "http://www.speedrun.com/api/v1/users/7j4ozn58"
          }
        ],
        "date": "2025-06-03",
        "submitted": "2025-06-12T08:08:15Z",
        "times": {
          "primary": "PT46M1S",
          "primary_t": 2761,
          "realtime": "PT1H4M59S",
          "realtime_t": 3899,
          "realtime_noloads": "PT46M1S",
          "realtime_noloads_t": 2761,
          "ingame": null,
          "ingame_t": 0
        },
        "system": {
          "platform": "n5e17e27",
          "emulated": true,
          "region": "e6lxy1dz"
        },
        "splits": null,
        "values": {
          "yn20gk2l": "qvv4y7rq"
        }
      }
    },
    {
      "place": 14,
      "run": {
        "id": "y22q976y",
        "weblink": "http://www.speedrun.com/hp2ps2/run/y22q976y",
        "game": "pd0n7o21",
        "level": null,
        "category": "rklo0owk",
        "videos": {
          "links": [
            {
              "uri": "https://youtu.be/RqiyXg9azkc"
            }
          ]
        },
        "comment": "gg this run is great",
        "status": {
          "status": "verified",
          "examiner": "j5v9dw68",
          "verify-date": "2024-02-23T22:14:30Z"
        },
        "players": [
          {
            "rel": "user",
            "id": "8r2ko2qx",
            "uri": "http://www.speedrun.com/api/v1/users/8r2ko2qx"
          }
        ],
        "date": "2022-06-10",
        "submitted": "2024-02-23T22:14:30Z",
        "times": {
          "primary": "PT46M15S",
          "primary_t": 2775,
          "realtime": "PT1H11M27S",
          "realtime_t": 4287,
          "realtime_noloads": "PT46M15S",
          "realtime_noloads_t": 2775,
          "ingame": null,
          "ingame_t": 0
        },
        "system": {
          "platform": "n5e17e27",
          "emulated": false,
          "region": "pr184lqn"
        },
        "splits": null,
        "values": {
          "yn20gk2l": "139v60r1"
        }
      }
    },
    {
      "place": 15,
      "run": {
        "id": "yld43ekm",
        "weblink": "http://www.speedrun.com/hp2ps2/run/yld43ekm",
        "game": "pd0n7o21",
        "level": null,
        "category": "rklo0owk",
        "videos": {
          "links": [
            {
              "uri": "https://www.twitch.tv/videos/1571460837"
            }
          ]
        },
        "comment": "movie",
        "status": {
          "status": "verified",
          "examiner": "j5v9dw68",
          "verify-date": "2024-02-23T22:17:52Z"
        },
        "players": [
          {
            "rel": "user",
            "id": "8wly5w3j",
            "uri": "http://www.speedrun.com/api/v1/users/8wly5w3j"
          }
        ],
        "date": "2022-08-24",
        "submitted": "2024-02-23T22:17:52Z",
        "times": {
          "primary": "PT47M15S",
          "primary_t": 2835,
          "realtime": "PT1H13M2S",
          "realtime_t": 4382,
          "realtime_noloads": "PT47M15S",
          "realtime_noloads_t": 2835,
          "ingame": null,
          "ingame_t": 0
        },
        "system": {
          "platform": "n5e17e27",
          "emulated": false,
          "region": "e6lxy1dz"
        },
        "splits": null,
        "values": {
          "yn20gk2l": "139v60r1"
        }
      }
    },
    {
      "place": 16,
      "run": {
        "id": "zn24we3z",
        "weblink": "http://www.speedrun.com/hp2ps2/run/zn24we3z",
        "game": "pd0n7o21",
        "level": null,
        "category": "rklo0owk",
        "videos": {
          "links": [
            {
              "uri": "https://youtu.be/vJX0YM4nHHc"
            }
          ]
        },
        "comment": "I don't think I can do any better at the moment",
        "status": {
          "status": "verified",
          "examiner": "j5v9dw68",
          "verify-date": "2024-02-23T23:02:40Z"
        },
        "players": [
          {
            "rel": "user",
            "id": "j9p9rw7x",
            "uri": "http://www.speedrun.com/api/v1/users/j9p9rw7x"
          }
        ],
        "date": "2023-06-08",
        "submitted": "2024-02-23T23:02:40Z",
        "times": {
          "primary": "PT47M26S",
          "primary_t": 2846,
          "realtime": "PT1H3M57S",
          "realtime_t": 3837,
          "realtime_noloads": "PT47M26S",
          "realtime_noloads_t": 2846,
          "ingame": null,
          "ingame_t": 0
        },
        "system": {
          "platform": "n5e17e27",
          "emulated": true,
          "region": "pr184lqn"
        },
        "splits": null,
        "values": {
          "yn20gk2l": "qvv4y7rq"
        }
      }
    },
    {
      "place": 17,
      "run": {
        "id": "m7opp30y",
        "weblink": "http://www.speedrun.com/hp2ps2/run/m7opp30y",
        "game": "pd0n7o21",
        "level": null,
        "category": "rklo0owk",
        "videos": {
          "links": [
            {
              "uri": "https://youtu.be/iPfPcttEsT8"
            }
          ]
        },
        "comment": "Achieved my goal of beating Nixxo's time lol",
        "status": {
          "status": "verified",
          "examiner": "j5v9dw68",
          "verify-date": "2024-07-17T14:01:02Z"
        },
        "players": [
          {
            "rel": "user",
            "id": "j2wqqrpj",
            "uri": "http://www.speedrun.com/api/v1/users/j2wqqrpj"
          }
        ],
        "date": "2024-07-17",
        "submitted": "2024-07-17T03:07:15Z",
        "times": {
          "primary": "PT47M28S",
          "primary_t": 2848,
          "realtime": "PT1H6M3S",
          "realtime_t": 3963,
          "realtime_noloads": "PT47M28S",
          "realtime_noloads_t": 2848,
          "ingame": null,
          "ingame_t": 0
        },
        "system": {
          "platform": "n5e17e27",
          "emulated": true,
          "region": "pr184lqn"
        },
        "splits": null,
        "values": {
          "yn20gk2l": "qvv4y7rq"
        }
      }
    },
    {
      "place": 18,
      "run": {
        "id": "mrv8j62z",
        "weblink": "http://www.speedrun.com/hp2ps2/run/mrv8j62z",
        "game": "pd0n7o21",
        "level": null,
        "category": "rklo0owk",
        "videos": {
          "links": [
            {
              "uri": "https://www.youtube.com/watch?v=30ezTF79zj4"
            }
          ]
        },
        "comment": null,
        "status": {
          "status": "verified",
          "examiner": "j5v9dw68",
          "verify-date": "2025-03-04T00:05:38Z"
        },
        "players": [
          {
            "rel": "user",
            "id": "5j5lwknx",
            "uri": "http://www.speedrun.com/api/v1/users/5j5lwknx"
          }
        ],
        "date": "2023-01-25",
        "submitted": "2024-02-23T22:20:10Z",
        "times": {
          "primary": "PT48M",
          "primary_t": 2880,
          "realtime": "PT1H14M29S",
          "realtime_t": 4469,
          "realtime_noloads": "PT48M",
          "realtime_noloads_t": 2880,
          "ingame": null,
          "ingame_t": 0
        },
        "system": {
          "platform": "n5e17e27",
          "emulated": false,
          "region": "e6lxy1dz"
        },
        "splits": null,
        "values": {
          "yn20gk2l": "139v60r1"
        }
      }
    },
    {
      "place": 19,
      "run": {
        "id": "ywgpeg0z",
        "weblink": "http://www.speedrun.com/hp2ps2/run/ywgpeg0z",
        "game": "pd0n7o21",
        "level": null,
        "category": "rklo0owk",
        "videos": {
          "links": [
            {
              "uri": "https://www.twitch.tv/videos/1118691100"
            }
          ]
        },
        "comment": null,
        "status": {
          "status": "verified",
          "examiner": "j5v9dw68",
          "verify-date": "2024-02-23T23:08:11Z"
        },
        "players": [
          {
            "rel": "user",
            "id": "j4q0ynwx",
            "uri": "http://www.speedrun.com/api/v1/users/j4q0ynwx"
          }
        ],
        "date": "2021-08-14",
        "submitted": "2024-02-23T23:08:11Z",
        "times": {
          "primary": "PT48M22S",
          "primary_t": 2902,
          "realtime": "PT1H5M33S",
          "realtime_t": 3933,
          "realtime_noloads": "PT48M22S",
          "realtime_noloads_t": 2902,
          "ingame": null,
          "ingame_t": 0
        },
        "system": {
          "platform": "n5e17e27",
          "emulated": true,
          "region": "pr184lqn"
        },
        "splits": null,
        "values": {
          "yn20gk2l": "qvv4y7rq"
        }
      }
    },
    {
      "place": 20,
      "run": {
        "id": "y2npo27y",
        "weblink": "http://www.speedrun.com/hp2ps2/run/y2npo27y",
        "game": "pd0n7o21",
        "level": null,
        "category": "rklo0owk",
        "videos": {
          "links": [
            {
              "uri": "https://youtu.be/kLD4xGKm5tg"
            }
          ]
        },
        "comment": "Another one for my quest to run all the pre-HP4 categories, pretty alright run, messed up Willow skip twice",
        "status": {
          "status": "verified",
          "examiner": "j5v9dw68",
          "verify-date": "2025-04-01T23:05:01Z"
        },
        "players": [
          {
            "rel": "user",
            "id": "3qjooej6",
            "uri": "http://www.speedrun.com/api/v1/users/3qjooej6"
          }
        ],
        "date": "2025-02-01",
        "submitted": "2025-02-01T22:23:06Z",
        "times": {
          "primary": "PT48M50S",
          "primary_t": 2930,
          "realtime": "PT1H14M49S",
          "realtime_t": 4489,
          "realtime_noloads": "PT48M50S",
          "realtime_noloads_t": 2930,
          "ingame": null,
          "ingame_t": 0
        },
        "system": {
          "platform": "n5e17e27",
          "emulated": false,
          "region": "e6lxy1dz"
        },
        "splits": null,
        "values": {
          "yn20gk2l": "139v60r1"
        }
      }
    },
    {
      "place": 21,
      "run": {
        "id": "y9j2ojkm",
        "weblink": "http://www.speedrun.com/hp2ps2/run/y9j2ojkm",
        "game": "pd0n7o21",
        "level": null,
        "category": "rklo0owk",
        "videos": {
          "links": [
            {
              "uri": "https://youtu.be/tfqNB168-T4"
            }
          ]
        },
        "comment": null,
        "status": {
          "status": "verified",
          "examiner": "j5v9dw68",
          "verify-date": "2024-02-23T23:09:19Z"
        },
        "players": [
          {
            "rel": "user",
            "id": "xzl7v048",
            "uri": "http://www.speedrun.com/api/v1/users/xzl7v048"
          }
        ],
        "date": "2022-11-28",
        "submitted": "2024-02-23T23:09:19Z",
        "times": {
          "primary": "PT49M4S",
          "primary_t": 2944,
          "realtime": "PT1H6M16S",
          "realtime_t": 3976,
          "realtime_noloads": "PT49M4S",
          "realtime_noloads_t": 2944,
          "ingame": null,
          "ingame_t": 0
        },
        "system": {
          "platform": "n5e17e27",
          "emulated": true,
          "region": "e6lxy1dz"
        },
        "splits": {
          "rel": "splits.io",
          "uri": "https://splits.io/api/v3/runs/a8nk"
        },
        "values": {
          "yn20gk2l": "qvv4y7rq"
        }
      }
    },
    {
      "place": 22,
      "run": {
        "id": "mew8ve9m",
        "weblink": "http://www.speedrun.com/hp2ps2/run/mew8ve9m",
        "game": "pd0n7o21",
        "level": null,
        "category": "rklo0owk",
        "videos": {
          "links": [
            {
              "uri": "https://youtu.be/nuWexSgzU5g"
            }
          ]
        },
        "comment": "nice saves",
        "status": {
          "status": "verified",
          "examiner": "j5v9dw68",
          "verify-date": "2024-02-23T22:44:14Z"
        },
        "players": [
          {
            "rel": "user",
            "id": "x35p5eqj",
            "uri": "http://www.speedrun.com/api/v1/users/x35p5eqj"
          }
        ],
        "date": "2021-12-31",
        "submitted": "2024-02-23T22:44:14Z",
        "times": {
          "primary": "PT49M26S",
          "primary_t": 2966,
          "realtime": "PT1H15M39S",
          "realtime_t": 4539,
          "realtime_noloads": "PT49M26S",
          "realtime_noloads_t": 2966,
          "ingame": null,
          "ingame_t": 0
        },
        "system": {
          "platform": "n5e17e27",
          "emulated": false,
          "region": "pr184lqn"
        },
        "splits": null,
        "values": {
          "yn20gk2l": "139v60r1"
        }
      }
    },
    {
      "place": 23,
      "run": {
        "id": "m7np1nez",
        "weblink": "http://www.speedrun.com/hp2ps2/run/m7np1nez",
        "game": "pd0n7o21",
        "level": null,
        "category": "rklo0owk",
        "videos": {
          "links": [
            {
              "uri": "https://youtu.be/WmMpy46-rZ0"
            }
          ]
        },
        "comment": "It didn't softlock and corrupt my Burrow save again so I actually finished. Pretty happy with it overall, glad to have a run on my favourite childhood hp game. Shame about the whole \"not playing most of it\" part.",
        "status": {
          "status": "verified",
          "examiner": "j5v9dw68",
          "verify-date": "2024-02-23T23:10:25Z"
        },
        "players": [
          {
            "rel": "user",
            "id": "jmpd624j",
            "uri": "http://www.speedrun.com/api/v1/users/jmpd624j"
          }
        ],
        "date": "2021-08-03",
        "submitted": "2024-02-23T23:10:25Z",
        "times": {
          "primary": "PT49M43S",
          "primary_t": 2983,
          "realtime": "PT1H6M30S",
          "realtime_t": 3990,
          "realtime_noloads": "PT49M43S",
          "realtime_noloads_t": 2983,
          "ingame": null,
          "ingame_t": 0
        },
        "system": {
          "platform": "n5e17e27",
          "emulated": true,
          "region": "pr184lqn"
        },
        "splits": null,
        "values": {
          "yn20gk2l": "qvv4y7rq"
        }
      }
    },
    {
      "place": 24,
      "run": {
        "id": "yo0xdq0y",
        "weblink": "http://www.speedrun.com/hp2ps2/run/yo0xdq0y",
        "game": "pd0n7o21",
        "level": null,
        "category": "rklo0owk",
        "videos": {
          "links": [
            {
              "uri": "https://youtu.be/F1wia76DFnE"
            }
          ]
        },
        "comment": null,
        "status": {
          "status": "verified",
          "examiner": "8l049d48",
          "verify-date": "2024-05-21T01:09:23Z"
        },
        "players": [
          {
            "rel": "user",
            "id": "8gm7yn18",
            "uri": "http://www.speedrun.com/api/v1/users/8gm7yn18"
          }
        ],
        "date": "2024-05-21",
        "submitted": "2024-05-21T00:45:11Z",
        "times": {
          "primary": "PT50M49S",
          "primary_t": 3049,
          "realtime": "PT1H9M7S",
          "realtime_t": 4147,
          "realtime_noloads": "PT50M49S",
          "realtime_noloads_t": 3049,
          "ingame": null,
          "ingame_t": 0
        },
        "system": {
          "platform": "n5e17e27",
          "emulated": false,
          "region": null
        },
        "splits": null,
        "values": {
          "yn20gk2l": "qvv4y7rq"
        }
      }
    },
    {
      "place": 25,
      "run": {
        "id": "yld43xrm",
        "weblink": "http://www.speedrun.com/hp2ps2/run/yld43xrm",
        "game": "pd0n7o21",
        "level": null,
        "category": "rklo0owk",
        "videos": {
          "links": [
            {
              "uri": "https://youtu.be/WkvnVKOLQVI"
            }
          ]
        },
        "comment": "Had this sat on my pc for a while but never submitted it. Need to run this again tbh\n\nBut yes, PBed slightly in this run so was happy :)",
        "status": {
          "status": "verified",
          "examiner": "j5v9dw68",
          "verify-date": "2024-02-23T23:15:49Z"
        },
        "players": [
          {
            "rel": "user",
            "id": "j5v9dw68",
            "uri": "http://www.speedrun.com/api/v1/users/j5v9dw68"
          }
        ],
        "date": "2021-08-21",
        "submitted": "2024-02-23T23:15:49Z",
        "times": {
          "primary": "PT58M29S",
          "primary_t": 3509,
          "realtime": "PT1H16M23S",
          "realtime_t": 4583,
          "realtime_noloads": "PT58M29S",
          "realtime_noloads_t": 3509,
          "ingame": null,
          "ingame_t": 0
        },
        "system": {
          "platform": "n5e17e27",
          "emulated": true,
          "region": "pr184lqn"
        },
        "splits": null,
        "values": {
          "yn20gk2l": "qvv4y7rq"
        }
      }
    },
    {
      "place": 26,
      "run": {
        "id": "yld43nkm",
        "weblink": "http://www.speedrun.com/hp2ps2/run/yld43nkm",
        "game": "pd0n7o21",
        "level": null,
        "category": "rklo0owk",
        "videos": {
          "links": [
            {
              "uri": "https://youtu.be/KhjUUTTaxjU"
            }
          ]
        },
        "comment": "wow this run sucked",
        "status": {
          "status": "verified",
          "examiner": "j5v9dw68",
          "verify-date": "2024-02-23T22:43:06Z"
        },
        "players": [
          {
            "rel": "user",
            "id": "qjn1lq8m",
            "uri": "http://www.speedrun.com/api/v1/users/qjn1lq8m"
          }
        ],
        "date": "2021-02-12",
        "submitted": "2024-02-23T22:43:06Z",
        "times": {
          "primary": "PT1H3M14S",
          "primary_t": 3794,
          "realtime": "PT1H37M44S",
          "realtime_t": 5864,
          "realtime_noloads": "PT1H3M14S",
          "realtime_noloads_t": 3794,
          "ingame": null,
          "ingame_t": 0
        },
        "system": {
          "platform": "n5e17e27",
          "emulated": false,
          "region": "pr184lqn"
        },
        "splits": null,
        "values": {
          "yn20gk2l": "139v60r1"
        }
      }
    }
  ],
  "scrapedAt": "2026-03-01T16:41:27.758Z"
}